macroecon_tools/__init__.py
macroecon_tools/constants.py
macroecon_tools/fetch_data.py
macroecon_tools/timeseries.py
macroecon_tools/visualizer.py
macroecon_tools-2.0.2.dist-info/licenses/LICENSE
macroecon_tools-2.0.2.dist-info/METADATA
macroecon_tools-2.0.2.dist-info/WHEEL
macroecon_tools-2.0.2.dist-info/entry_points.txt
macroecon_tools-2.0.2.dist-info/top_level.txt
macroecon_tools-2.0.2.dist-info/RECORD
