Metadata-Version: 2.4
Name: macroecon-tools
Version: 2.0.2
Summary: Suite of tools for macroeconomics analysis
Author-email: Nathaniel Throckmorton <nathrockmorton@wm.edu>, Jawand Singh <jawandsingh@gmail.com>
License: GNU GENERAL PUBLIC LICENSE
Project-URL: repository, https://github.com/nathrock/nonlinear-macro/tree/main/Python/macroecon-tools
Keywords: macroeconomics,tool,analysis,data
Classifier: License :: OSI Approved :: GNU General Public License v3 (GPLv3)
Classifier: Programming Language :: Python :: 3
Requires-Python: >=3.9
License-File: LICENSE
Requires-Dist: fredapi>=0.5.1
Requires-Dist: numpy>=1.24.1
Requires-Dist: pandas>=1.5.2
Requires-Dist: scipy>=1.12.0
Requires-Dist: matplotlib
Requires-Dist: quantecon
Requires-Dist: scikit-learn
Requires-Dist: openpyxl
Requires-Dist: jinja2>=3.1.2
Requires-Dist: tabulate>=0.9.0
Requires-Dist: statsmodels>=0.14.4
Dynamic: license-file
